README.md
setup.py
meimbalance2/__init__.py
meimbalance2.egg-info/PKG-INFO
meimbalance2.egg-info/SOURCES.txt
meimbalance2.egg-info/dependency_links.txt
meimbalance2.egg-info/requires.txt
meimbalance2.egg-info/top_level.txt
meimbalance2/common/__init__.py
meimbalance2/common/env.py
meimbalance2/common/mienums.py
meimbalance2/datalake/_Datalake.py
meimbalance2/datalake/_DatalakeGen2.py
meimbalance2/datalake/_ImbalanceDatalakes.py
meimbalance2/datalake/__init__.py
meimbalance2/datalake/utils.py
meimbalance2/mail/__init__.py
meimbalance2/mail/_mail.py
meimbalance2/sms/__init__.py
meimbalance2/sms/_sms.py
meimbalance2/sql/__init__.py
meimbalance2/sql/data.py
meimbalance2/sql/log.py
meimbalance2/sql/common/__init__.py
meimbalance2/sql/common/_common.py
test/meimbalance_tests/__init__.py
test/meimbalance_tests/datalake_tests/__init__.py
test/meimbalance_tests/datalake_tests/utils_tests.py
test/meimbalance_tests/sql_tests/__init__.py
test/meimbalance_tests/sql_tests/common_tests.py