Metadata-Version: 2.1
Name: meimbalance2
Version: 0.0.2
Summary: A helper package for the Imbalance project
Author: Håkon Klausen
Author-email: hakon.klausen@ae.no
License: UNKNOWN
Platform: UNKNOWN
Requires-Python: >=3.7
